zhutils/__init__.py
zhutils/adv.py
zhutils/attacks.py
zhutils/demo.py
zhutils/lib.py
zhutils/models.py
zhutils/simphy.py
zhutils/tpatch.py
zhutils/utils.py
zhutils/vis.py
zhutils/third_party/__init__.py
zhutils/third_party/facenet/__init__.py
zhutils/third_party/facenet/setup.py
zhutils/third_party/facenet/models/__init__.py
zhutils/third_party/facenet/models/inception_resnet_v1.py
zhutils/third_party/facenet/models/mtcnn.py
zhutils/third_party/facenet/models/utils/__init__.py
zhutils/third_party/facenet/models/utils/detect_face.py
zhutils/third_party/facenet/models/utils/download.py
zhutils/third_party/facenet/models/utils/tensorflow2pytorch.py
zhutils/third_party/facenet/models/utils/training.py
zhutils/third_party/facerecog/__init__.py
zhutils/third_party/facerecog/facenet.py
zhutils/third_party/facerecog/ir152.py
zhutils/third_party/facerecog/irse.py
zhutils/third_party/yolov5/__init__.py
zhutils/third_party/yolov5/models/__init__.py
zhutils/third_party/yolov5/models/common.py
zhutils/third_party/yolov5/models/experimental.py
zhutils/third_party/yolov5/models/tf.py
zhutils/third_party/yolov5/models/yolo.py
zhutils/third_party/yolov5/utils/__init__.py
zhutils/third_party/yolov5/utils/activations.py
zhutils/third_party/yolov5/utils/augmentations.py
zhutils/third_party/yolov5/utils/autoanchor.py
zhutils/third_party/yolov5/utils/autobatch.py
zhutils/third_party/yolov5/utils/benchmarks.py
zhutils/third_party/yolov5/utils/callbacks.py
zhutils/third_party/yolov5/utils/datasets.py
zhutils/third_party/yolov5/utils/downloads.py
zhutils/third_party/yolov5/utils/general.py
zhutils/third_party/yolov5/utils/loss.py
zhutils/third_party/yolov5/utils/metrics.py
zhutils/third_party/yolov5/utils/plots.py
zhutils/third_party/yolov5/utils/torch_utils.py
zhutils/third_party/yolov5/utils/aws/__init__.py
zhutils/third_party/yolov5/utils/aws/resume.py
zhutils/third_party/yolov5/utils/loggers/__init__.py
zhutils/third_party/yolov5/utils/loggers/wandb/__init__.py
zhutils-0.6.1.dist-info/METADATA
zhutils-0.6.1.dist-info/WHEEL
zhutils-0.6.1.dist-info/top_level.txt
zhutils-0.6.1.dist-info/RECORD
