Metadata-Version: 2.1
Name: zhutils
Version: 0.6.1
Summary: UNKNOWN
Home-page: UNKNOWN
Author: forget2save
License: UNKNOWN
Platform: UNKNOWN
Requires-Dist: torch (>=1.7)
Requires-Dist: torchvision (>=0.8)
Requires-Dist: seaborn
